sparkle_test/__init__.py
sparkle_test/test_case.py
sparkle_test-1.2.0.dist-info/LICENSE
sparkle_test-1.2.0.dist-info/WHEEL
sparkle_test-1.2.0.dist-info/METADATA
sparkle_test-1.2.0.dist-info/RECORD
