Metadata-Version: 2.1
Name: sparkle-test
Version: 1.2.0
Summary: 
Author: Machiel Keizer-Groeneveld
Author-email: machiel.groeneveldkeizer@vodafoneziggo.com
Requires-Python: >=3.7.1,<4
Classifier: Programming Language :: Python :: 3
Classifier: Programming Language :: Python :: 3.10
Classifier: Programming Language :: Python :: 3.8
Classifier: Programming Language :: Python :: 3.9
Requires-Dist: pandas (==1.3.5)
